game_vision/__init__.py
game_vision/detector.py
game_vision/exceptions.py
game_vision/trainer.py
game_vision/utils.py
game_vision-1.0.0.dist-info/METADATA
game_vision-1.0.0.dist-info/WHEEL
game_vision-1.0.0.dist-info/top_level.txt
game_vision-1.0.0.dist-info/RECORD
