Metadata-Version: 2.4
Name: game-vision
Version: 1.0.0
Summary: Easy-to-use wrapper for training and inference of game object detection models (YOLOv8)
Author: Alex
Author-email: thettboy11@gmail.com
Keywords: yolo object-detection computer-vision game ai machine-learning
Classifier: Development Status :: 5 - Production/Stable
Classifier: Intended Audience :: Developers
Classifier: License :: OSI Approved :: MIT License
Classifier: Programming Language :: Python :: 3
Classifier: Programming Language :: Python :: 3.8
Classifier: Programming Language :: Python :: 3.9
Classifier: Programming Language :: Python :: 3.10
Classifier: Programming Language :: Python :: 3.11
Classifier: Topic :: Scientific/Engineering :: Artificial Intelligence
Requires-Python: >=3.8
Requires-Dist: torch>=1.9.0
Requires-Dist: ultralytics>=8.0.0
Requires-Dist: opencv-python>=4.5.0
Requires-Dist: numpy>=1.21.0
Requires-Dist: onnxruntime>=1.12.0
Provides-Extra: gpu
Requires-Dist: onnxruntime-gpu>=1.12.0; extra == "gpu"
Provides-Extra: dev
Requires-Dist: pytest>=6.0; extra == "dev"
Requires-Dist: black>=22.0; extra == "dev"
Requires-Dist: flake8>=4.0; extra == "dev"
Requires-Dist: mypy>=0.900; extra == "dev"
Dynamic: author
Dynamic: author-email
Dynamic: classifier
Dynamic: description-content-type
Dynamic: keywords
Dynamic: provides-extra
Dynamic: requires-dist
Dynamic: requires-python
Dynamic: summary
